lht/__init__.cpython-313-darwin.so
lht/__init__.py
lht/cli/__init__.cpython-313-darwin.so
lht/cli/__init__.py
lht/cli/commands/__init__.cpython-313-darwin.so
lht/cli/commands/__init__.py
lht/cli/commands/connect.cpython-313-darwin.so
lht/cli/commands/create_connection.cpython-313-darwin.so
lht/cli/commands/edit_connection.cpython-313-darwin.so
lht/cli/commands/list_connections.cpython-313-darwin.so
lht/cli/commands/set_primary.cpython-313-darwin.so
lht/cli/commands/sync_sobject.cpython-313-darwin.so
lht/salesforce/__init__.cpython-313-darwin.so
lht/salesforce/__init__.py
lht/salesforce/ingest_bapi20.cpython-313-darwin.so
lht/salesforce/intelligent_sync.cpython-313-darwin.so
lht/salesforce/query_bapi20.cpython-313-darwin.so
lht/salesforce/results_bapi.cpython-313-darwin.so
lht/salesforce/retl.cpython-313-darwin.so
lht/salesforce/sobject_create.cpython-313-darwin.so
lht/salesforce/sobject_query.cpython-313-darwin.so
lht/salesforce/sobject_sync.cpython-313-darwin.so
lht/salesforce/sobjects.cpython-313-darwin.so
lht/sflake/query.cpython-313-darwin.so
lht/user/__init__.cpython-313-darwin.so
lht/user/__init__.py
lht/user/auth.cpython-313-darwin.so
lht/user/salesforce_auth.cpython-313-darwin.so
lht/user/connections/__init__.cpython-313-darwin.so
lht/user/connections/__init__.py
lht/user/connections/manager.cpython-313-darwin.so
lht/util/__init__.cpython-313-darwin.so
lht/util/__init__.py
lht/util/csv.cpython-313-darwin.so
lht/util/data_writer.cpython-313-darwin.so
lht/util/field_types.cpython-313-darwin.so
lht/util/file.cpython-313-darwin.so
lht/util/log_retl.cpython-313-darwin.so
lht/util/merge.cpython-313-darwin.so
lht/util/soql_query.cpython-313-darwin.so
lht/util/stage.cpython-313-darwin.so
lht/util/table_creator.cpython-313-darwin.so
lht-2.0.11.dist-info/licenses/LICENSE
lht-2.0.11.dist-info/METADATA
lht-2.0.11.dist-info/WHEEL
lht-2.0.11.dist-info/entry_points.txt
lht-2.0.11.dist-info/top_level.txt,sha256=a1fb7e4ecb8fb71365a5e26853327401773dbdab5cf9c9089226a27dbc0090d8,4lht-2.0.11.dist-info/RECORD
