Metadata-Version: 2.4
Name: lht
Version: 2.0.11
Summary: Lakehouse Tools for Snowflake and Salesforce
Author-email: LHT Author <dan@solomo.io>
Project-URL: Homepage, https://github.com/pypa/lht
Project-URL: Issues, https://github.com/pypa/lht/issues
Classifier: Programming Language :: Python :: 3
Classifier: License :: OSI Approved :: MIT License
Classifier: Operating System :: OS Independent
Requires-Python: >=3.9
License-File: LICENSE
Requires-Dist: pandas>=2.2.3
Requires-Dist: snowflake-snowpark-python>=1.31.1
Requires-Dist: requests>=2.32.3
Requires-Dist: cryptography>=3.0.0
Requires-Dist: pyarrow>=10.0.0
Dynamic: license-file
